XRetriever/__init__.py
XRetriever/matcher.py
XRetriever/peak_detector.py
XRetriever/retriever.py
XRetriever/xrd_reader.py
xretriever-0.1.0.dist-info/METADATA
xretriever-0.1.0.dist-info/WHEEL
xretriever-0.1.0.dist-info/top_level.txt
xretriever-0.1.0.dist-info/RECORD
